atsphinx/sqlite3fts/__init__.py
atsphinx/sqlite3fts/builders.py
atsphinx/sqlite3fts/cli.py
atsphinx/sqlite3fts/events.py
atsphinx/sqlite3fts/models.py
atsphinx/sqlite3fts/services.py
atsphinx/sqlite3fts/utils.py
atsphinx/sqlite3fts/static/searchtools.js
atsphinx_sqlite3fts-0.1.4.dist-info/entry_points.txt
atsphinx_sqlite3fts-0.1.4.dist-info/LICENSE
atsphinx_sqlite3fts-0.1.4.dist-info/WHEEL
atsphinx_sqlite3fts-0.1.4.dist-info/METADATA
atsphinx_sqlite3fts-0.1.4.dist-info/RECORD
